pytrackunit/__init__.py
pytrackunit/helper.py
pytrackunit/sqlcache.py
pytrackunit/trackunit.py
pytrackunit/tucache.py
pytrackunit/tuiter.py
pytrackunit/webcache.py
pytrackunit-2.4.1.dist-info/LICENSE
pytrackunit-2.4.1.dist-info/METADATA
pytrackunit-2.4.1.dist-info/WHEEL
pytrackunit-2.4.1.dist-info/top_level.txt
pytrackunit-2.4.1.dist-info/RECORD
