Metadata-Version: 2.1
Name: pytrackunit
Version: 2.4.1
Summary: Easy access for TrackUnit REST API
Home-page: https://github.com/einsteinmaster/TrackUnitPython
Author: Marius Schlueter
Author-email: themrslue@googlemail.com
License: UNKNOWN
Project-URL: Bug Tracker, https://github.com/einsteinmaster/TrackUnitPython/issues
Platform: UNKNOWN
Classifier: Programming Language :: Python :: 3
Classifier: License :: OSI Approved :: MIT License
Classifier: Operating System :: OS Independent
Requires-Python: >=3.8
License-File: LICENSE
Requires-Dist: aiohttp
Requires-Dist: aiofiles
Requires-Dist: tqdm
Requires-Dist: python-dateutil
Requires-Dist: aiosqlite
Requires-Dist: aioprocessing
